{
    "ver": "5.0",
    "tag": "hipsuser",
    "data": [
        {
            "id": 256,
            "power": 0,
            "name": "Telemetry.TerminalServer.A",
            "procname": "*",
            "treatment": 1,
            "policies": [
                {
                    "montype": 2,
                    "action_type": 4,
                    "res_path": "*\\SYSTEM\\CurrentControlSet\\Control\\Terminal Server\\WinStations\\RDP-Tcp\\InitialProgram"
                }
            ]
        }
    ]
}